[
  {
  	"id": 0,
    "name": "me",
    "answer": "me",
  	"type": "gesture",
  	"video": "https://media.spreadthesign.com/video/mp4/13/48587.mp4"
  },
  {
  	"id": 1,
    "name": "hungry",
    "answer": "hungry",
  	"type": "gesture",
  	"video": "https://media.spreadthesign.com/video/mp4/13/58529.mp4"
  },
  {
  	"id": 2,
    "name": "i am hungry",
    "answer": "me hungry",
  	"type": "text",
  	"video": "https://media.spreadthesign.com/video/mp4/13/93471.mp4"
  },
  {
  	"id": 3,
  	"answer": "you",
  	"type": "gesture",
  	"video": "https://media.spreadthesign.com/video/mp4/13/51110.mp4"
  },
  {
  	"id": 4,
  	"answer": "are you hungry?",
  	"type": "gesture",
  	"video": "https://media.spreadthesign.com/video/mp4/13/89928.mp4"
  },
  {
  	"id": 5,
  	"answer": "want",
  	"type": "gesture",
  	"video": "https://media.spreadthesign.com/video/mp4/13/50936.mp4"
  },
  {
  	"id": 6,
  	"answer": "i want this",
  	"type": "text",
  	"video": "https://media.spreadthesign.com/video/mp4/13/73478.mp4"
  }
]